dadata/__init__.py
dadata/asynchr.py
dadata/settings.py
dadata/sync.py
dadata-25.7.0.dist-info/WHEEL
dadata-25.7.0.dist-info/METADATA
dadata-25.7.0.dist-info/RECORD
