Metadata-Version: 2.3
Name: dadata
Version: 25.7.0
Summary: Data cleansing, enrichment and suggestions via Dadata API
Keywords: dadata,clean,suggest,api
Classifier: License :: OSI Approved :: MIT License
Classifier: Programming Language :: Python :: 3
Requires-Dist: httpx
Requires-Python: >=3.9
Project-URL: Source, https://github.com/hflabs/dadata-py
